odoo/addons/pms_rooming_xls/README.rst
odoo/addons/pms_rooming_xls/__init__.py
odoo/addons/pms_rooming_xls/__manifest__.py
odoo/addons/pms_rooming_xls/i18n/es.po
odoo/addons/pms_rooming_xls/i18n/pms_rooming_xls.pot
odoo/addons/pms_rooming_xls/i18n/report_xlsx_helper_demo.pot
odoo/addons/pms_rooming_xls/models/__init__.py
odoo/addons/pms_rooming_xls/models/pms_checkin_partner.py
odoo/addons/pms_rooming_xls/models/pms_folio.py
odoo/addons/pms_rooming_xls/readme/CONTRIBUTORS.rst
odoo/addons/pms_rooming_xls/readme/DESCRIPTION.rst
odoo/addons/pms_rooming_xls/readme/USAGE.rst
odoo/addons/pms_rooming_xls/report/__init__.py
odoo/addons/pms_rooming_xls/report/rooming_checkin_xlsx.py
odoo/addons/pms_rooming_xls/security/ir.model.access.csv
odoo/addons/pms_rooming_xls/static/description/icon.png
odoo/addons/pms_rooming_xls/static/description/index.html
odoo/addons/pms_rooming_xls/views/pms_folio.xml
odoo/addons/pms_rooming_xls/wizard/__init__.py
odoo/addons/pms_rooming_xls/wizard/import_rooming_xlsx.py
odoo/addons/pms_rooming_xls/wizard/import_rooming_xlsx.xml
odoo14_addon_pms_rooming_xls-14.0.1.0.1.dev10.dist-info/METADATA
odoo14_addon_pms_rooming_xls-14.0.1.0.1.dev10.dist-info/WHEEL
odoo14_addon_pms_rooming_xls-14.0.1.0.1.dev10.dist-info/top_level.txt
odoo14_addon_pms_rooming_xls-14.0.1.0.1.dev10.dist-info/RECORD
